hcgf/__init__.py
hcgf/__main_infer__.py
hcgf/__main_tune__.py
hcgf/base.py
hcgf/data_model/__init__.py
hcgf/dataloader/__init__.py
hcgf/dataloader/data_collector.py
hcgf/dataloader/data_loader.py
hcgf/dataloader/dataset.py
hcgf/dataloader/preprocessor.py
hcgf/rm/__init__.py
hcgf/rm/ft.py
hcgf/rm/reward_model.py
hcgf/sft/__init__.py
hcgf/sft/base.py
hcgf/sft/ft.py
hcgf/sft/ia3/__init__.py
hcgf/sft/ia3/ia3_config.py
hcgf/sft/ia3/ia3_layer.py
hcgf/sft/ia3/ia3_layer_8bit.py
hcgf/sft/ia3/ia3_model.py
hcgf/sft/lora/__init__.py
hcgf/sft/lora/lora_config.py
hcgf/sft/lora/lora_layer.py
hcgf/sft/lora/lora_layer_8bit.py
hcgf/sft/lora/lora_model.py
hcgf/trainer/__init__.py
hcgf/trainer/fsdp.py
hcgf/trainer/trainer.py
hcgf/utils/__init__.py
hcgf/utils/utils.py
hcgf-0.4.2.dist-info/LICENSE
hcgf-0.4.2.dist-info/METADATA
hcgf-0.4.2.dist-info/WHEEL
hcgf-0.4.2.dist-info/entry_points.txt
hcgf-0.4.2.dist-info/top_level.txt
hcgf-0.4.2.dist-info/RECORD
