Metadata-Version: 2.1
Name: hcgf
Version: 0.4.2
Summary: Humanable Chat Generative-model Fine-tuning.
Home-page: https://github.com/hscspring/hcgf
Author: Yam
Author-email: haoshaochun@gmail.com
Classifier: Programming Language :: Python :: 3
Classifier: License :: OSI Approved :: Apache Software License
Classifier: Operating System :: OS Independent
License-File: LICENSE
Requires-Dist: cpm-kernels
Requires-Dist: transformers
Requires-Dist: pnlp
Requires-Dist: gradio
